kmy/__init__.py
kmy/account.py
kmy/address.py
kmy/costcenter.py
kmy/fileinfo.py
kmy/institution.py
kmy/institutionaddress.py
kmy/kmy.py
kmy/payee.py
kmy/payeeaddress.py
kmy/split.py
kmy/subaccount.py
kmy/tag.py
kmy/transaction.py
kmy/user.py
kmy/useraddress.py
kmy-0.0.3.dist-info/LICENSE
kmy-0.0.3.dist-info/METADATA
kmy-0.0.3.dist-info/WHEEL
kmy-0.0.3.dist-info/top_level.txt
kmy-0.0.3.dist-info/RECORD
